Homevee/API.py
Homevee/CloudConnection.py
Homevee/CommandLine.py
Homevee/SmartSpeakerConnection.py
Homevee/__init__.py
Homevee/AIAgents/__init__.py
Homevee/AIAgents/ImageClassifier/ARControlClassifier.py
Homevee/AIAgents/ImageClassifier/PeopleClassifier.py
Homevee/AIAgents/ImageClassifier/__init__.py
Homevee/AIAgents/ImageClassifierRetrainer/ARControlRetrainer.py
Homevee/AIAgents/ImageClassifierRetrainer/PeopleClassifierRetrainer.py
Homevee/AIAgents/ImageClassifierRetrainer/__init__.py
Homevee/APIModule/APIKeyAPIModule.py
Homevee/APIModule/AutomationAPIModule.py
Homevee/APIModule/BlindsAPIModule.py
Homevee/APIModule/CalendarAPIModule.py
Homevee/APIModule/ChatAPIModule.py
Homevee/APIModule/CustomVoiceCommandAPIModule.py
Homevee/APIModule/DashboardAPIModule.py
Homevee/APIModule/DeviceAPIModule.py
Homevee/APIModule/DimmerAPIModule.py
Homevee/APIModule/EnergyDataAPIModule.py
Homevee/APIModule/EventAPIModule.py
Homevee/APIModule/GPSDataAPIModule.py
Homevee/APIModule/GatewayAPIModule.py
Homevee/APIModule/GraphDataAPIModule.py
Homevee/APIModule/HeatingSchemeAPIModule.py
Homevee/APIModule/HomeBudgetAPIModule.py
Homevee/APIModule/LoginAPIModule.py
Homevee/APIModule/MQTTConnectorAPIModule.py
Homevee/APIModule/MediaCenterAPIModule.py
Homevee/APIModule/NutritionDataAPIModule.py
Homevee/APIModule/PersonAPIModule.py
Homevee/APIModule/PlaceAPIModule.py
Homevee/APIModule/RBGLightAPIModule.py
Homevee/APIModule/RFIDTagAPIModule.py
Homevee/APIModule/RemoteControlAPIModule.py
Homevee/APIModule/RoomAPIModule.py
Homevee/APIModule/RoomDataAPIModule.py
Homevee/APIModule/SceneAPIModule.py
Homevee/APIModule/SensorDataAPIModule.py
Homevee/APIModule/ShoppingListAPIModule.py
Homevee/APIModule/SmartSpeakerAPIModule.py
Homevee/APIModule/SystemInfoAPIModule.py
Homevee/APIModule/TVPlanAPIModule.py
Homevee/APIModule/ThermostatAPIModule.py
Homevee/APIModule/UpdaterAPIModule.py
Homevee/APIModule/UserAPIModule.py
Homevee/APIModule/VoiceAPIModule.py
Homevee/APIModule/WakeOnLanAPIModule.py
Homevee-0.1.1.36.dist-info/METADATA
Homevee-0.1.1.36.dist-info/WHEEL
Homevee-0.1.1.36.dist-info/entry_points.txt
Homevee-0.1.1.36.dist-info/top_level.txt
Homevee-0.1.1.36.dist-info/RECORD
