Metadata-Version: 2.1
Name: Homevee
Version: 0.1.1.36
Summary: Dein neues Smarthome-System!
Home-page: https://github.com/Homevee/Homevee
Author: Homevee
Author-email: support@Homevee.de
License: UNKNOWN
Platform: UNKNOWN
Classifier: Programming Language :: Python :: 3.6
Classifier: License :: OSI Approved :: MIT License
Classifier: Operating System :: OS Independent
Requires-Dist: packaging
Requires-Dist: python-dateutil
Requires-Dist: pyOpenSSL
Requires-Dist: pymax
Requires-Dist: paho-mqtt
Requires-Dist: Pillow
Requires-Dist: passlib
Requires-Dist: numpy
Requires-Dist: azure-iothub-device-client
Requires-Dist: flask
Requires-Dist: psutil
